cli_project/main.py
release_test_cli-1.0.0.dist-info/METADATA
release_test_cli-1.0.0.dist-info/WHEEL
release_test_cli-1.0.0.dist-info/entry_points.txt
release_test_cli-1.0.0.dist-info/RECORD
