Metadata-Version: 2.4
Name: release-test-cli
Version: 1.0.0
Summary: CLI tool for release testing
Project-URL: Homepage, https://github.com/malhotra5/release-test
Project-URL: Repository, https://github.com/malhotra5/release-test.git
Author-email: Release Test <test@example.com>
Requires-Python: >=3.8
Requires-Dist: click>=8.0.0
Requires-Dist: requests>=2.28.0
